setup.py
formulation/__init__.py
formulation.egg-info/PKG-INFO
formulation.egg-info/SOURCES.txt
formulation.egg-info/dependency_links.txt
formulation.egg-info/not-zip-safe
formulation.egg-info/top_level.txt
formulation/templates/formulation/default.form
formulation/templatetags/__init__.py
formulation/templatetags/formulation.py
formulation/templatetags/reuse.py