Metadata-Version: 1.1
Name: formulation
Version: 2.0.13
Summary: Django Form rendering tool
Home-page: UNKNOWN
Author: Curtis Maloney
Author-email: curtis@tinbrain.net
License: UNKNOWN
Keywords: django,forms,templates
Platform: UNKNOWN
Classifier: Environment :: Web Environment
Classifier: Framework :: Django
Classifier: License :: OSI Approved :: BSD License
Classifier: Operating System :: OS Independent
Classifier: Programming Language :: Python
Classifier: Programming Language :: Python :: 2
Classifier: Programming Language :: Python :: 2.7
Classifier: Programming Language :: Python :: 3
Classifier: Programming Language :: Python :: 3.3
Classifier: Programming Language :: Python :: 3.4
Classifier: Programming Language :: Python :: Implementation :: PyPy
